{
  "layout": "normal",
  "name": "Alesha's Vanguard",
  "manaCost": "{3}{B}",
  "cmc": 4,
  "colors": [
    "Black"
  ],
  "type": "Creature — Orc Warrior",
  "types": [
    "Creature"
  ],
  "subtypes": [
    "Orc",
    "Warrior"
  ],
  "text": "Dash {2}{B} (You may cast this spell for its dash cost. If you do, it gains haste, and it's returned from the battlefield to its owner's hand at the beginning of the next end step.)",
  "power": "3",
  "toughness": "3",
  "imageName": "alesha's vanguard",
  "colorIdentity": [
    "B"
  ]
}