{
  "layout": "normal",
  "name": "Asmira, Holy Avenger",
  "manaCost": "{2}{G}{W}",
  "cmc": 4,
  "colors": [
    "White",
    "Green"
  ],
  "type": "Legendary Creature — Human Cleric",
  "supertypes": [
    "Legendary"
  ],
  "types": [
    "Creature"
  ],
  "subtypes": [
    "Human",
    "Cleric"
  ],
  "text": "Flying\nAt the beginning of each end step, put a +1/+1 counter on Asmira, Holy Avenger for each creature put into your graveyard from the battlefield this turn.",
  "power": "2",
  "toughness": "3",
  "imageName": "asmira, holy avenger",
  "colorIdentity": [
    "W",
    "G"
  ]
}