{
  "layout": "normal",
  "name": "Baleful Eidolon",
  "manaCost": "{1}{B}",
  "cmc": 2,
  "colors": [
    "Black"
  ],
  "type": "Enchantment Creature — Spirit",
  "types": [
    "Enchantment",
    "Creature"
  ],
  "subtypes": [
    "Spirit"
  ],
  "text": "Bestow {4}{B} (If you cast this card for its bestow cost, it's an Aura spell with enchant creature. It becomes a creature again if it's not attached to a creature.)\nDeathtouch (Any amount of damage this deals to a creature is enough to destroy it.)\nEnchanted creature gets +1/+1 and has deathtouch.",
  "power": "1",
  "toughness": "1",
  "imageName": "baleful eidolon",
  "colorIdentity": [
    "B"
  ]
}