{
  "layout": "normal",
  "name": "Broodhatch Nantuko",
  "manaCost": "{1}{G}",
  "cmc": 2,
  "colors": [
    "Green"
  ],
  "type": "Creature — Insect Druid",
  "types": [
    "Creature"
  ],
  "subtypes": [
    "Insect",
    "Druid"
  ],
  "text": "Whenever Broodhatch Nantuko is dealt damage, you may create that many 1/1 green Insect creature tokens.\nMorph {2}{G} (You may cast this card face down as a 2/2 creature for {3}. Turn it face up any time for its morph cost.)",
  "power": "1",
  "toughness": "1",
  "imageName": "broodhatch nantuko",
  "colorIdentity": [
    "G"
  ]
}