{
  "layout": "normal",
  "name": "Drownyard Explorers",
  "manaCost": "{3}{U}",
  "cmc": 4,
  "colors": [
    "Blue"
  ],
  "type": "Creature — Human Wizard",
  "types": [
    "Creature"
  ],
  "subtypes": [
    "Human",
    "Wizard"
  ],
  "text": "When Drownyard Explorers enters the battlefield, investigate. (Create a colorless Clue artifact token with \"{2}, Sacrifice this artifact: Draw a card.\")",
  "power": "2",
  "toughness": "4",
  "imageName": "drownyard explorers",
  "colorIdentity": [
    "U"
  ]
}