{
  "layout": "normal",
  "name": "Entropic Eidolon",
  "manaCost": "{3}{B}",
  "cmc": 4,
  "colors": [
    "Black"
  ],
  "type": "Creature — Spirit",
  "types": [
    "Creature"
  ],
  "subtypes": [
    "Spirit"
  ],
  "text": "{B}, Sacrifice Entropic Eidolon: Target player loses 1 life and you gain 1 life.\nWhenever you cast a multicolored spell, you may return Entropic Eidolon from your graveyard to your hand.",
  "power": "2",
  "toughness": "2",
  "imageName": "entropic eidolon",
  "colorIdentity": [
    "B"
  ]
}