{
  "layout": "normal",
  "name": "Gonti, Lord of Luxury",
  "manaCost": "{2}{B}{B}",
  "cmc": 4,
  "colors": [
    "Black"
  ],
  "type": "Legendary Creature — Aetherborn Rogue",
  "supertypes": [
    "Legendary"
  ],
  "types": [
    "Creature"
  ],
  "subtypes": [
    "Aetherborn",
    "Rogue"
  ],
  "text": "Deathtouch\nWhen Gonti, Lord of Luxury enters the battlefield, look at the top four cards of target opponent's library, exile one of them face down, then put the rest on the bottom of that library in a random order. For as long as that card remains exiled, you may look at it, you may cast it, and you may spend mana as though it were mana of any type to cast it.",
  "power": "2",
  "toughness": "3",
  "imageName": "gonti, lord of luxury",
  "colorIdentity": [
    "B"
  ]
}