{
  "layout": "normal",
  "name": "Grief Tyrant",
  "manaCost": "{5}{B/R}",
  "cmc": 6,
  "colors": [
    "Black",
    "Red"
  ],
  "type": "Creature — Horror",
  "types": [
    "Creature"
  ],
  "subtypes": [
    "Horror"
  ],
  "text": "Grief Tyrant enters the battlefield with four -1/-1 counters on it.\nWhen Grief Tyrant dies, put a -1/-1 counter on target creature for each -1/-1 counter on Grief Tyrant.",
  "power": "8",
  "toughness": "8",
  "imageName": "grief tyrant",
  "colorIdentity": [
    "B",
    "R"
  ]
}