{
  "layout": "normal",
  "name": "Heliod's Emissary",
  "manaCost": "{3}{W}",
  "cmc": 4,
  "colors": [
    "White"
  ],
  "type": "Enchantment Creature — Elk",
  "types": [
    "Enchantment",
    "Creature"
  ],
  "subtypes": [
    "Elk"
  ],
  "text": "Bestow {6}{W} (If you cast this card for its bestow cost, it's an Aura spell with enchant creature. It becomes a creature again if it's not attached to a creature.)\nWhenever Heliod's Emissary or enchanted creature attacks, tap target creature an opponent controls.\nEnchanted creature gets +3/+3.",
  "power": "3",
  "toughness": "3",
  "imageName": "heliod's emissary",
  "colorIdentity": [
    "W"
  ]
}