{
  "layout": "flip",
  "name": "Homura, Human Ascendant",
  "names": [
    "Homura, Human Ascendant",
    "Homura's Essence"
  ],
  "manaCost": "{4}{R}{R}",
  "cmc": 6,
  "colors": [
    "Red"
  ],
  "type": "Legendary Creature — Human Monk",
  "supertypes": [
    "Legendary"
  ],
  "types": [
    "Creature"
  ],
  "subtypes": [
    "Human",
    "Monk"
  ],
  "text": "Homura, Human Ascendant can't block.\nWhen Homura dies, return it to the battlefield flipped.",
  "power": "4",
  "toughness": "4",
  "imageName": "homura, human ascendant",
  "colorIdentity": [
    "R"
  ]
}