{
  "layout": "normal",
  "name": "Impromptu Raid",
  "manaCost": "{3}{R/G}",
  "cmc": 4,
  "colors": [
    "Red",
    "Green"
  ],
  "type": "Enchantment",
  "types": [
    "Enchantment"
  ],
  "text": "{2}{R/G}: Reveal the top card of your library. If it isn't a creature card, put it into your graveyard. Otherwise, put that card onto the battlefield. That creature gains haste. Sacrifice it at the beginning of the next end step.",
  "imageName": "impromptu raid",
  "colorIdentity": [
    "R",
    "G"
  ]
}