{
  "layout": "normal",
  "name": "Increasing Vengeance",
  "manaCost": "{R}{R}",
  "cmc": 2,
  "colors": [
    "Red"
  ],
  "type": "Instant",
  "types": [
    "Instant"
  ],
  "text": "Copy target instant or sorcery spell you control. If Increasing Vengeance was cast from a graveyard, copy that spell twice instead. You may choose new targets for the copies.\nFlashback {3}{R}{R} (You may cast this card from your graveyard for its flashback cost. Then exile it.)",
  "imageName": "increasing vengeance",
  "colorIdentity": [
    "R"
  ]
}