{
  "layout": "normal",
  "name": "Keeper of Keys",
  "manaCost": "{3}{U}{U}",
  "cmc": 5,
  "colors": [
    "Blue"
  ],
  "type": "Creature — Human Rogue Mutant",
  "types": [
    "Creature"
  ],
  "subtypes": [
    "Human",
    "Rogue",
    "Mutant"
  ],
  "text": "When Keeper of Keys enters the battlefield, you become the monarch.\nAt the beginning of your upkeep, if you're the monarch, creatures you control can't be blocked this turn.",
  "power": "4",
  "toughness": "4",
  "imageName": "keeper of keys",
  "colorIdentity": [
    "U"
  ]
}