{
  "layout": "normal",
  "name": "Munda, Ambush Leader",
  "manaCost": "{2}{R}{W}",
  "cmc": 4,
  "colors": [
    "White",
    "Red"
  ],
  "type": "Legendary Creature — Kor Ally",
  "supertypes": [
    "Legendary"
  ],
  "types": [
    "Creature"
  ],
  "subtypes": [
    "Kor",
    "Ally"
  ],
  "text": "Haste\nRally — Whenever Munda, Ambush Leader or another Ally enters the battlefield under your control, you may look at the top four cards of your library. If you do, reveal any number of Ally cards from among them, then put those cards on top of your library in any order and the rest on the bottom in any order.",
  "power": "3",
  "toughness": "4",
  "imageName": "munda, ambush leader",
  "colorIdentity": [
    "W",
    "R"
  ]
}