{
  "layout": "normal",
  "name": "Profaner of the Dead",
  "manaCost": "{3}{U}",
  "cmc": 4,
  "colors": [
    "Blue"
  ],
  "type": "Creature — Naga Wizard",
  "types": [
    "Creature"
  ],
  "subtypes": [
    "Naga",
    "Wizard"
  ],
  "text": "Exploit (When this creature enters the battlefield, you may sacrifice a creature.)\nWhen Profaner of the Dead exploits a creature, return to their owners' hands all creatures your opponents control with toughness less than the exploited creature's toughness.",
  "power": "3",
  "toughness": "3",
  "imageName": "profaner of the dead",
  "colorIdentity": [
    "U"
  ]
}