{
  "layout": "normal",
  "name": "Return to the Ranks",
  "manaCost": "{X}{W}{W}",
  "cmc": 2,
  "colors": [
    "White"
  ],
  "type": "Sorcery",
  "types": [
    "Sorcery"
  ],
  "text": "Convoke (Your creatures can help cast this spell. Each creature you tap while casting this spell pays for {1} or one mana of that creature's color.)\nReturn X target creature cards with converted mana cost 2 or less from your graveyard to the battlefield.",
  "imageName": "return to the ranks",
  "colorIdentity": [
    "W"
  ]
}