{
  "layout": "normal",
  "name": "Savage Thallid",
  "manaCost": "{3}{G}{G}",
  "cmc": 5,
  "colors": [
    "Green"
  ],
  "type": "Creature — Fungus",
  "types": [
    "Creature"
  ],
  "subtypes": [
    "Fungus"
  ],
  "text": "At the beginning of your upkeep, put a spore counter on Savage Thallid.\nRemove three spore counters from Savage Thallid: Create a 1/1 green Saproling creature token.\nSacrifice a Saproling: Regenerate target Fungus.",
  "power": "5",
  "toughness": "2",
  "imageName": "savage thallid",
  "colorIdentity": [
    "G"
  ]
}