{
  "layout": "normal",
  "name": "Sensei Golden-Tail",
  "manaCost": "{1}{W}",
  "cmc": 2,
  "colors": [
    "White"
  ],
  "type": "Legendary Creature — Fox Samurai",
  "supertypes": [
    "Legendary"
  ],
  "types": [
    "Creature"
  ],
  "subtypes": [
    "Fox",
    "Samurai"
  ],
  "text": "Bushido 1 (Whenever this creature blocks or becomes blocked, it gets +1/+1 until end of turn.)\n{1}{W}, {T}: Put a training counter on target creature. That creature gains bushido 1 and becomes a Samurai in addition to its other creature types. Activate this ability only any time you could cast a sorcery.",
  "power": "2",
  "toughness": "1",
  "imageName": "sensei golden-tail",
  "colorIdentity": [
    "W"
  ]
}