{
  "layout": "normal",
  "name": "Shape Anew",
  "manaCost": "{3}{U}",
  "cmc": 4,
  "colors": [
    "Blue"
  ],
  "type": "Sorcery",
  "types": [
    "Sorcery"
  ],
  "text": "The controller of target artifact sacrifices it, then reveals cards from the top of his or her library until he or she reveals an artifact card. That player puts that card onto the battlefield, then shuffles all other cards revealed this way into his or her library.",
  "imageName": "shape anew",
  "colorIdentity": [
    "U"
  ]
}