{
  "layout": "normal",
  "name": "Skinshifter",
  "manaCost": "{1}{G}",
  "cmc": 2,
  "colors": [
    "Green"
  ],
  "type": "Creature — Human Shaman",
  "types": [
    "Creature"
  ],
  "subtypes": [
    "Human",
    "Shaman"
  ],
  "text": "{G}: Choose one —\n• Until end of turn, Skinshifter becomes a Rhino with base power and toughness 4/4 and gains trample. Activate this ability only once each turn.\n• Until end of turn, Skinshifter becomes a Bird with base power and toughness 2/2 and gains flying. Activate this ability only once each turn.\n• Until end of turn, Skinshifter becomes a Plant with base power and toughness 0/8. Activate this ability only once each turn.",
  "power": "1",
  "toughness": "1",
  "imageName": "skinshifter",
  "colorIdentity": [
    "G"
  ]
}