{
  "layout": "normal",
  "name": "Ulasht, the Hate Seed",
  "manaCost": "{2}{R}{G}",
  "cmc": 4,
  "colors": [
    "Red",
    "Green"
  ],
  "type": "Legendary Creature — Hellion Hydra",
  "supertypes": [
    "Legendary"
  ],
  "types": [
    "Creature"
  ],
  "subtypes": [
    "Hellion",
    "Hydra"
  ],
  "text": "Ulasht, the Hate Seed enters the battlefield with a +1/+1 counter on it for each other red creature you control and a +1/+1 counter on it for each other green creature you control.\n{1}, Remove a +1/+1 counter from Ulasht: Choose one —\n• Ulasht deals 1 damage to target creature.\n• Put a 1/1 green Saproling creature token onto the battlefield.",
  "power": "0",
  "toughness": "0",
  "imageName": "ulasht, the hate seed",
  "colorIdentity": [
    "R",
    "G"
  ]
}