{
  "layout": "double-faced",
  "name": "Ulvenwald Mystics",
  "names": [
    "Ulvenwald Mystics",
    "Ulvenwald Primordials"
  ],
  "manaCost": "{2}{G}{G}",
  "cmc": 4,
  "colors": [
    "Green"
  ],
  "type": "Creature — Human Shaman Werewolf",
  "types": [
    "Creature"
  ],
  "subtypes": [
    "Human",
    "Shaman",
    "Werewolf"
  ],
  "text": "At the beginning of each upkeep, if no spells were cast last turn, transform Ulvenwald Mystics.",
  "power": "3",
  "toughness": "3",
  "imageName": "ulvenwald mystics",
  "colorIdentity": [
    "G"
  ]
}