{
  "layout": "normal",
  "name": "Wingbeat Warrior",
  "manaCost": "{2}{W}",
  "cmc": 3,
  "colors": [
    "White"
  ],
  "type": "Creature — Bird Soldier Warrior",
  "types": [
    "Creature"
  ],
  "subtypes": [
    "Bird",
    "Soldier",
    "Warrior"
  ],
  "text": "Flying\nMorph {2}{W} (You may cast this card face down as a 2/2 creature for {3}. Turn it face up any time for its morph cost.)\nWhen Wingbeat Warrior is turned face up, target creature gains first strike until end of turn.",
  "power": "2",
  "toughness": "1",
  "imageName": "wingbeat warrior",
  "colorIdentity": [
    "W"
  ]
}